AUTHORS
HISTORY.rst
LICENSE
MANIFEST.in
README.rst
setup.py
docs/.DS_Store
docs/Makefile
docs/conf.py
docs/definitions.rst
docs/exg.rst
docs/gui.rst
docs/history.rst
docs/index.rst
docs/license.rst
docs/mock.rst
docs/utils.rst
docs/_build/.buildinfo
docs/_build/changes.html
docs/_build/definitions.html
docs/_build/exg.html
docs/_build/genindex.html
docs/_build/gui.html
docs/_build/history.html
docs/_build/index.html
docs/_build/license.html
docs/_build/mock.html
docs/_build/objects.inv
docs/_build/py-modindex.html
docs/_build/search.html
docs/_build/searchindex.js
docs/_build/utils.html
docs/_build/.doctrees/changes.doctree
docs/_build/.doctrees/definitions.doctree
docs/_build/.doctrees/environment.pickle
docs/_build/.doctrees/exg.doctree
docs/_build/.doctrees/gui.doctree
docs/_build/.doctrees/history.doctree
docs/_build/.doctrees/index.doctree
docs/_build/.doctrees/license.doctree
docs/_build/.doctrees/mock.doctree
docs/_build/.doctrees/utils.doctree
docs/_build/_images/ekg.png
docs/_build/_sources/changes.txt
docs/_build/_sources/definitions.txt
docs/_build/_sources/exg.txt
docs/_build/_sources/gui.txt
docs/_build/_sources/history.txt
docs/_build/_sources/index.txt
docs/_build/_sources/license.txt
docs/_build/_sources/mock.txt
docs/_build/_sources/utils.txt
docs/_build/_static/ajax-loader.gif
docs/_build/_static/basic.css
docs/_build/_static/comment-bright.png
docs/_build/_static/comment-close.png
docs/_build/_static/comment.png
docs/_build/_static/default.css
docs/_build/_static/doctools.js
docs/_build/_static/down-pressed.png
docs/_build/_static/down.png
docs/_build/_static/file.png
docs/_build/_static/jquery.js
docs/_build/_static/minus.png
docs/_build/_static/plus.png
docs/_build/_static/pygments.css
docs/_build/_static/searchtools.js
docs/_build/_static/sidebar.js
docs/_build/_static/underscore.js
docs/_build/_static/up-pressed.png
docs/_build/_static/up.png
docs/_build/_static/websupport.js
docs/_build/doctrees/definitions.doctree
olimex_ekg_emg.egg-info/PKG-INFO
olimex_ekg_emg.egg-info/SOURCES.txt
olimex_ekg_emg.egg-info/dependency_links.txt
olimex_ekg_emg.egg-info/requires.txt
olimex_ekg_emg.egg-info/top_level.txt
