Metadata-Version: 1.1
Name: olimex-ekg-emg
Version: 0.2.0
Summary: A package for gathering data from the Olimex EKG/EMG Shield.
Home-page: https://github.com/logston/olimex-ekg-emg
Author: Paul Logston
Author-email: code@logston.me
License: olimex-ekg-emg:
